README.md
setup.cfg
setup.py
rv_distributions/Binomialdistribution.py
rv_distributions/Gaussiandistribution.py
rv_distributions/Generaldistribution.py
rv_distributions/__init__.py
rv_distributions.egg-info/PKG-INFO
rv_distributions.egg-info/SOURCES.txt
rv_distributions.egg-info/dependency_links.txt
rv_distributions.egg-info/not-zip-safe
rv_distributions.egg-info/top_level.txt