Metadata-Version: 1.0
Name: rv-distributions
Version: 1.0
Summary: Random variables distributions
Home-page: UNKNOWN
Author: Thibaut Koutangni
Author-email: koutibaut@yahoo.fr
License: UNKNOWN
Platform: UNKNOWN
